{"title":"슈프라이즈 ─ 해외","url":"https://www.shoeprize.com/today/?filter={%22excludeKor%22:1,%22includeKor%22:0,%22excludeEnd%22:0}","favicon":"https://static.shoeprize.com/images/icons/appIcon/touch-icon-16x16.1d3df1c84440.png","elements":[{"title":"아디다스 오리지널스 자메이카 그레이 식스 엘로우","contents":"ATMOS TOKYO","link":"https://www.shoeprize.com/raffles/400315","retrieved":1707837003574},{"title":"아디다스 오리지널스 슈퍼스타 코어 블랙 옐로우 컬리지에이트 그린","contents":"ATMOS TOKYO","link":"https://www.shoeprize.com/raffles/400314","retrieved":1707837003576},{"title":"아디다스 오리지널스 삼바 OG 코어 블랙 옐로우 컬리지에이트 그린","contents":"ATMOS TOKYO","link":"https://www.shoeprize.com/raffles/397659","retrieved":1707837003577},{"title":"아디다스 오리지널스 삼바 OG 클라우드 화이트 옐로우 컬리지에이트 그린","contents":"ATMOS TOKYO","link":"https://www.shoeprize.com/raffles/397658","retrieved":1707837003578},{"title":"에어 조던 3 크래프트 아이보리","contents":"END","link":"https://www.shoeprize.com/raffles/114455","retrieved":1707837003580},{"title":"에어 조던 1 하이 OG TD 화이트 골드","contents":"END","link":"https://www.shoeprize.com/raffles/396026","retrieved":1707837003581},{"title":"에어 조던 1 하이 OG PS 화이트 골드","contents":"END","link":"https://www.shoeprize.com/raffles/396025","retrieved":1707837003582},{"title":"에어 조던 1 하이 OG 우먼스 화이트 골드","contents":"END","link":"https://www.shoeprize.com/raffles/114457","retrieved":1707837003584},{"title":"에어 조던 2 로우 파이썬","contents":"END","link":"https://www.shoeprize.com/raffles/119434","retrieved":1707837003585},{"title":"나이키 줌 보메로 5 우먼스 그린 모스","contents":"NIKE JP","link":"https://www.shoeprize.com/raffles/396457","retrieved":1707837003586},{"title":"나이키 줌 보메로 5 우먼스 새턴 골드","contents":"NIKE JP","link":"https://www.shoeprize.com/raffles/393015","retrieved":1707837003588},{"title":"에어 조던 1 하이 OG TD 화이트 골드","contents":"NIKE JP","link":"https://www.shoeprize.com/raffles/396026","retrieved":1707837003581},{"title":"에어 조던 1 하이 OG PS 화이트 골드","contents":"NIKE JP","link":"https://www.shoeprize.com/raffles/396025","retrieved":1707837003582},{"title":"에어 조던 1 하이 OG 우먼스 화이트 골드","contents":"NIKE JP","link":"https://www.shoeprize.com/raffles/114457","retrieved":1707837003584},{"title":"나이키 줌 보메로 5 레이크사이드","contents":"NIKE JP","link":"https://www.shoeprize.com/raffles/390842","retrieved":1707837003593},{"title":"에어 조던 1 하이 OG 우먼스 화이트 골드","contents":"FOOTDISTRICT","link":"https://www.shoeprize.com/raffles/114457","retrieved":1707837003584},{"title":"나이키 줌 보메로 5 레이크사이드","contents":"ATMOS TOKYO","link":"https://www.shoeprize.com/raffles/390842","retrieved":1707837003593},{"title":"에어 조던 1 하이 OG TD 화이트 골드","contents":"ATMOS TOKYO","link":"https://www.shoeprize.com/raffles/396026","retrieved":1707837003581},{"title":"에어 조던 1 하이 OG PS 화이트 골드","contents":"ATMOS TOKYO","link":"https://www.shoeprize.com/raffles/396025","retrieved":1707837003582},{"title":"에어 조던 1 하이 OG 우먼스 화이트 골드","contents":"ATMOS TOKYO","link":"https://www.shoeprize.com/raffles/114457","retrieved":1707837003584},{"title":"에어 조던 1 하이 OG TD 화이트 골드","contents":"나이키 코리아","link":"https://www.shoeprize.com/raffles/396026","retrieved":1707837003581},{"title":"에어 조던 1 하이 OG PS 화이트 골드","contents":"나이키 코리아","link":"https://www.shoeprize.com/raffles/396025","retrieved":1707837003582},{"title":"에어 조던 1 하이 OG 우먼스 화이트 골드","contents":"나이키 코리아","link":"https://www.shoeprize.com/raffles/114457","retrieved":1707837003584},{"title":"뉴발란스 550 시 솔트 블랙","contents":"뉴발란스 명동 직영점","link":"https://www.shoeprize.com/raffles/393878","retrieved":1707840761539},{"title":"아디다스 오리지널스 핸드볼 스페지알 우먼스 클리어 핑크","contents":"무신사","link":"https://www.shoeprize.com/raffles/116791","retrieved":1707840761540},{"title":"아디다스 오리지널스 핸드볼 스페지알 블랙 검","contents":"무신사","link":"https://www.shoeprize.com/raffles/79858","retrieved":1707840761541},{"title":"뉴발란스 550 시 솔트 블랙","contents":"뉴발란스 홍대 플래그쉽스토어","link":"https://www.shoeprize.com/raffles/393878","retrieved":1707840761543},{"title":"뉴발란스 550 시 솔트 블랙","contents":"뉴발란스 강남 직영점","link":"https://www.shoeprize.com/raffles/393878","retrieved":1707840761544},{"title":"조 프레시굿즈 x 뉴발란스 990v4 메이드 인 USA 1998 인트로 화이트","contents":"뉴발란스 코리아","link":"https://www.shoeprize.com/raffles/390965","retrieved":1707840761545},{"title":"조 프레시굿즈 x 뉴발란스 990v4 메이드 인 USA 1998 아웃트로 블랙","contents":"뉴발란스 코리아","link":"https://www.shoeprize.com/raffles/389182","retrieved":1707840761547}]}