{"title":"슈프라이즈 ─ 해외","url":"https://www.shoeprize.com/today/?filter={%22excludeKor%22:1,%22includeKor%22:0,%22excludeEnd%22:0}","favicon":"https://static.shoeprize.com/images/icons/appIcon/touch-icon-16x16.1d3df1c84440.png","elements":[{"title":"나이스 킥스 x 아디다스 오리지널스 삼바 컨소시엄 컵","contents":"ADIDAS CONFIRMED *IN APP","link":"https://www.shoeprize.com/raffles/383857","retrieved":1700665860779},{"title":"스니커 폴리틱스 x 아디다스 오리지널스 삼바 컨소시엄 컵","contents":"ADIDAS CONFIRMED *IN APP","link":"https://www.shoeprize.com/raffles/386789","retrieved":1700665860793},{"title":"엑스트라 버터 x 아디다스 오리지널스 삼바 컨소시엄 컵","contents":"ADIDAS CONFIRMED *IN APP","link":"https://www.shoeprize.com/raffles/386788","retrieved":1700665860779},{"title":"나이키 에어 맥스 1 레드 스타더스트","contents":"EXTRABUTTER","link":"https://www.shoeprize.com/raffles/363939","retrieved":1700665860794},{"title":"에어 조던 1 하이 OG 모브","contents":"UP THERE STORE","link":"https://www.shoeprize.com/raffles/115709","retrieved":1700665860794},{"title":"OTTO 958 x 아식스 젤-플렉스키 프로 블랙 퍼플","contents":"ATMOS TOKYO","link":"https://www.shoeprize.com/raffles/117618","retrieved":1700665860794},{"title":"나이키 에어 베이퍼맥스 목 롬 라이트 스톤 앤 루미너스 그린","contents":"NIKE JP","link":"https://www.shoeprize.com/raffles/382857","retrieved":1700665860794},{"title":"나이키 에어 베이퍼맥스 목 롬 트리플 블랙","contents":"NIKE JP","link":"https://www.shoeprize.com/raffles/382144","retrieved":1700665860794},{"title":"아디다스 오리지널스 오즈가이아 우먼스 퍼티 모브","contents":"ATMOS TOKYO","link":"https://www.shoeprize.com/raffles/389930","retrieved":1700665860794},{"title":"나이키 에어 베이퍼맥스 목 롬 라이트 스톤 앤 루미너스 그린","contents":"ATMOS TOKYO","link":"https://www.shoeprize.com/raffles/382857","retrieved":1700665860794},{"title":"나이키 에어 베이퍼맥스 목 롬 트리플 블랙","contents":"ATMOS TOKYO","link":"https://www.shoeprize.com/raffles/382144","retrieved":1700665860794},{"title":"나이키 에어 맥스 1 유니버시티 블루","contents":"ATMOS TOKYO","link":"https://www.shoeprize.com/raffles/121901","retrieved":1700665860795},{"title":"언더마이카 x 아트모스 x 아식스 젤-카야노 14 페퍼 블랙","contents":"아식스 코리아","link":"https://www.shoeprize.com/raffles/389166","retrieved":1700665860796},{"title":"언더마이카 x 아트모스 x 아식스 젤-카야노 14 블랙 퓨어 실버","contents":"아식스 코리아","link":"https://www.shoeprize.com/raffles/389163","retrieved":1700665860799},{"title":"아디다스 오리지널스 진스 클라우드 화이트 컬리지에이트 그린","contents":"무신사","link":"https://www.shoeprize.com/raffles/384873","retrieved":1700665860799},{"title":"아디다스 오리지널스 진스 클라우드 화이트 컬리지에이트 네이비","contents":"무신사","link":"https://www.shoeprize.com/raffles/384874","retrieved":1700665860801},{"title":"아식스 조그 100S 화이트 블랙","contents":"아식스 코리아","link":"https://www.shoeprize.com/raffles/118091","retrieved":1700665860802},{"title":"아디다스 오리지널스 오즈가이아 우먼스 화이트","contents":"ATMOS TOKYO","link":"https://www.shoeprize.com/raffles/389553","retrieved":1700665860803},{"title":"뉴발란스 576 메이드 인 UK 네이비","contents":"뉴발란스 북촌 직영점","link":"https://www.shoeprize.com/raffles/389848","retrieved":1700665860805},{"title":"뉴발란스 576 메이드 인 UK 블랙 시멘트","contents":"뉴발란스 북촌 직영점","link":"https://www.shoeprize.com/raffles/387546","retrieved":1700665860806},{"title":"뉴발란스 576 메이드 인 UK 네이비","contents":"뉴발란스 명동 직영점","link":"https://www.shoeprize.com/raffles/389848","retrieved":1700665860805},{"title":"뉴발란스 576 메이드 인 UK 블랙 시멘트","contents":"뉴발란스 명동 직영점","link":"https://www.shoeprize.com/raffles/387546","retrieved":1700665860806},{"title":"뉴발란스 576 메이드 인 UK 네이비","contents":"뉴발란스 홍대 플래그쉽스토어","link":"https://www.shoeprize.com/raffles/389848","retrieved":1700665860805},{"title":"뉴발란스 576 메이드 인 UK 블랙 시멘트","contents":"뉴발란스 홍대 플래그쉽스토어","link":"https://www.shoeprize.com/raffles/387546","retrieved":1700665860806},{"title":"뉴발란스 576 메이드 인 UK 네이비","contents":"뉴발란스 강남 직영점","link":"https://www.shoeprize.com/raffles/389848","retrieved":1700665860805},{"title":"뉴발란스 576 메이드 인 UK 블랙 시멘트","contents":"뉴발란스 강남 직영점","link":"https://www.shoeprize.com/raffles/387546","retrieved":1700665860806},{"title":"뉴발란스 576 메이드 인 UK 네이비","contents":"뉴발란스 코리아","link":"https://www.shoeprize.com/raffles/389848","retrieved":1700665860805},{"title":"뉴발란스 576 메이드 인 UK 블랙 시멘트","contents":"뉴발란스 코리아","link":"https://www.shoeprize.com/raffles/387546","retrieved":1700665860806},{"title":"에어 조던 13 휘트","contents":"SVD *IN APP","link":"https://www.shoeprize.com/raffles/111422","retrieved":1700669557696},{"title":"나이키 덩크 로우 미드나잇 네이비 앤 바로크 브라운","contents":"SVD *IN APP","link":"https://www.shoeprize.com/raffles/363940","retrieved":1700669557697}]}