{"title":"슈프라이즈 ─ 국내","url":"https://www.shoeprize.com/today/?filter={%22excludeKor%22:0,%22includeKor%22:1,%22excludeEnd%22:0}","favicon":"https://static.shoeprize.kr/images/icons/appIcon/touch-icon-16x16.1d3df1c84440.png","elements":[{"title":"나이키 덩크 로우 우먼스 블랙 페이즐리","contents":"나이키 서울","link":"https://www.shoeprize.com/raffles/80919","retrieved":1644736160821},{"title":"에어 조던 1 미드 우먼스 라이트 멀베리","contents":"슈프라이즈","link":"https://www.shoeprize.com/raffles/80683","retrieved":1644682334648},{"title":"나이키 덩크 로우 핑크 폼 GS","contents":"ABC마트 그랜드스테이지","link":"https://www.shoeprize.com/raffles/20602","retrieved":1644682334651},{"title":"나이키 덩크 로우 챔피언쉽 코트 퍼플","contents":"ABC마트 그랜드스테이지","link":"https://www.shoeprize.com/raffles/80734","retrieved":1644646240741},{"title":"피스마이너스원 X 나이키 퀀도1","contents":"펄핏","link":"https://www.shoeprize.com/raffles/64542","retrieved":1644653595702},{"title":"메종 미하라 야스히로 블레이키 OG 솔 캔버스 로우탑 스니커 블랙","contents":"현대백화점 울산점","link":"https://www.shoeprize.com/raffles/16262","retrieved":1644682334654},{"title":"메종 미하라 야스히로 피터슨 OG 솔 스웨이드 로우탑 스니커 블랙","contents":"현대백화점 울산점","link":"https://www.shoeprize.com/raffles/79135","retrieved":1644682334654},{"title":"나이키 덩크 로우 디스럽트 2 데저트 브론즈","contents":"나이키 코리아","link":"https://www.shoeprize.com/raffles/81178","retrieved":1644682334647},{"title":"나이키 덩크 하이 블랙 앤 화이트 GS","contents":"나이키 이태원 BB 타운점","link":"https://www.shoeprize.com/raffles/80482","retrieved":1644736160837},{"title":"에어 조던 1 로우 골프 시카고","contents":"펄핏","link":"https://www.shoeprize.com/raffles/80975","retrieved":1644653595703}]}