{"title":"슈프라이즈 ─ 해외","url":"https://www.shoeprize.com/today/?filter={%22excludeKor%22:1,%22includeKor%22:0,%22excludeEnd%22:0}","favicon":"https://static.shoeprize.com/images/icons/appIcon/touch-icon-16x16.1d3df1c84440.png","elements":[{"title":"에어 조던 2 로우 체리우드","contents":"SHOP NICEKICKS","link":"https://www.shoeprize.com/raffles/104651","retrieved":1686841847157},{"title":"에어 조던 2 로우 체리우드","contents":"XHIBITION","link":"https://www.shoeprize.com/raffles/104651","retrieved":1686841847157},{"title":"에어 조던 2 로우 체리우드","contents":"SHOE PALACE","link":"https://www.shoeprize.com/raffles/104651","retrieved":1686841847157},{"title":"토트넘 홋스퍼 FC 2023/24 x 나이키 스타디움 홈 저지","contents":"나이키 코리아","link":"https://www.shoeprize.com/raffles/115554","retrieved":1687004125901},{"title":"FC 바르셀로나 2023/24 x 나이키 매치 홈 저지","contents":"나이키 코리아","link":"https://www.shoeprize.com/raffles/115553","retrieved":1687004125906},{"title":"파리 생제르맹 2023/24 x 나이키 매치 홈 저지","contents":"나이키 코리아","link":"https://www.shoeprize.com/raffles/115552","retrieved":1687000155990},{"title":"유벤투스 FC 23/24 x 아디다스 홈 저지","contents":"아디다스 코리아","link":"https://www.shoeprize.com/raffles/115551","retrieved":1687000155991},{"title":"FC 바이에른 23/24 x 아디다스 홈 저지","contents":"아디다스 코리아","link":"https://www.shoeprize.com/raffles/115550","retrieved":1687000155992},{"title":"아스널 FC 23/24 x 아디다스 홈 저지","contents":"아디다스 코리아","link":"https://www.shoeprize.com/raffles/115549","retrieved":1687000155993},{"title":"AC밀란 23/24 x 푸마 홈 져지 긴팔 레플리카","contents":"푸마 코리아","link":"https://www.shoeprize.com/raffles/115548","retrieved":1687000155999},{"title":"AC 밀란 23/24 x 푸마 홈 져지 어센틱 레플리카","contents":"푸마 코리아","link":"https://www.shoeprize.com/raffles/115547","retrieved":1686996602227},{"title":"AC 밀란 23/24 x 푸마 홈 져지 레플리카","contents":"푸마 코리아","link":"https://www.shoeprize.com/raffles/115546","retrieved":1686996602228},{"title":"보루시아 뮌헨글라트바흐 23/24 x 푸마 홈 져지 레플리카","contents":"푸마 코리아","link":"https://www.shoeprize.com/raffles/115545","retrieved":1686996602229},{"title":"스타드렌 FC 23/24 x 푸마 홈 져지 레플리카","contents":"푸마 코리아","link":"https://www.shoeprize.com/raffles/115544","retrieved":1686996602229},{"title":"BVB 보루시아 도르트문트 23/24 x 푸마 홈 어센틱 져지","contents":"푸마 코리아","link":"https://www.shoeprize.com/raffles/115543","retrieved":1686996602230},{"title":"BVB 보루시아 도르트문트 23/24 x 푸마 홈 져지","contents":"푸마 코리아","link":"https://www.shoeprize.com/raffles/115542","retrieved":1686996602231},{"title":"맨체스터 시티 FC 23/24 x 푸마 홈 져지 긴팔 레플리카","contents":"푸마 코리아","link":"https://www.shoeprize.com/raffles/115541","retrieved":1686996602232},{"title":"맨체스터 시티 FC 23/24 x 푸마 홈 져지 레플리카","contents":"푸마 코리아","link":"https://www.shoeprize.com/raffles/115540","retrieved":1686992990708},{"title":"뉴발란스 550 화이트 빈티지 인디고","contents":"FINISHLINE","link":"https://www.shoeprize.com/raffles/115539","retrieved":1686992990710},{"title":"뉴발란스 1906R 화이트 골드","contents":"FINISHLINE","link":"https://www.shoeprize.com/raffles/96129","retrieved":1686992990712},{"title":"아디다스 오리지널스 삼바 컬리지에이트 그린","contents":"카시나","link":"https://www.shoeprize.com/raffles/113230","retrieved":1686921176035},{"title":"에어 조던 5 크래프트","contents":"카시나","link":"https://www.shoeprize.com/raffles/105115","retrieved":1686928185910},{"title":"아디다스 오리지널스 삼바 크리스탈 화이트 클레이 스트라타","contents":"카시나","link":"https://www.shoeprize.com/raffles/113227","retrieved":1686921176035},{"title":"MCM x 크록스 클래식 클로그 베이지 아이리쉬 크림","contents":"MCM KOREA","link":"https://www.shoeprize.com/raffles/115444","retrieved":1686971481740},{"title":"MCM x 크록스 클래식 클로그 화이트 그린","contents":"MCM KOREA","link":"https://www.shoeprize.com/raffles/115443","retrieved":1686971481741},{"title":"아디다스 오리지널스 가젤 카본 오프 화이트","contents":"SNS US","link":"https://www.shoeprize.com/raffles/110184","retrieved":1686971481742},{"title":"아디다스 오리지널스 가젤 인도어 아크틱 퓨전 컬리지에이트 그린","contents":"CONSORTIUM","link":"https://www.shoeprize.com/raffles/114593","retrieved":1686971481744},{"title":"아디다스 오리지널스 가젤 인도어 아크틱 퓨전 컬리지에이트 그린","contents":"ASPHALTGOLD *IN APP","link":"https://www.shoeprize.com/raffles/114593","retrieved":1686971481744},{"title":"아디다스 오리지널스 가젤 인도어 아크틱 퓨전 컬리지에이트 그린","contents":"SNS US","link":"https://www.shoeprize.com/raffles/114593","retrieved":1686971481744},{"title":"나이키 덩크 로우 GS 포톤 더스트 미드나잇 네이비","contents":"FINISHLINE","link":"https://www.shoeprize.com/raffles/115526","retrieved":1686971481747}]}