{"title":"슈프라이즈 ─ 해외","url":"https://www.shoeprize.com/today/?filter={%22excludeKor%22:1,%22includeKor%22:0,%22excludeEnd%22:0}","favicon":"https://static.shoeprize.com/images/icons/appIcon/touch-icon-16x16.1d3df1c84440.png","elements":[{"title":"나이키 ISPA 링크 액시스 토탈 오렌지 앤 소닉 옐로우","contents":"FEATURE","link":"https://www.shoeprize.com/raffles/119888","retrieved":1694445023329},{"title":"에어 조던 4 레트로 TD 카카오 와우","contents":"TOPS &amp; BOTTOMS","link":"https://www.shoeprize.com/raffles/364316","retrieved":1694445023308},{"title":"에어 조던 4 레트로 PS 카카오 와우","contents":"TOPS &amp; BOTTOMS","link":"https://www.shoeprize.com/raffles/364317","retrieved":1694445023313},{"title":"에어 조던 4 GS 카카오 와우","contents":"TOPS &amp; BOTTOMS","link":"https://www.shoeprize.com/raffles/102571","retrieved":1694445023310},{"title":"에어 조던 1 로우 GS 카카오 와우","contents":"TOPS &amp; BOTTOMS","link":"https://www.shoeprize.com/raffles/113247","retrieved":1694495412503},{"title":"에어 조던 1 미드 SE PS 카카오 와우","contents":"FEATURE","link":"https://www.shoeprize.com/raffles/364318","retrieved":1694499145486},{"title":"에어 조던 4 레트로 PS 카카오 와우","contents":"FEATURE","link":"https://www.shoeprize.com/raffles/364317","retrieved":1694445023313},{"title":"에어 조던 4 레트로 TD 카카오 와우","contents":"FEATURE","link":"https://www.shoeprize.com/raffles/364316","retrieved":1694445023308},{"title":"에어 조던 1 로우 GS 카카오 와우","contents":"FEATURE","link":"https://www.shoeprize.com/raffles/113247","retrieved":1694495412503},{"title":"에어 조던 4 GS 카카오 와우","contents":"FEATURE","link":"https://www.shoeprize.com/raffles/102571","retrieved":1694445023310},{"title":"에어 조던 1 미드 GS 카카오 와우","contents":"FEATURE","link":"https://www.shoeprize.com/raffles/113265","retrieved":1694506372707},{"title":"에어 조던 1 미드 SE TD 카카오 와우","contents":"FEATURE","link":"https://www.shoeprize.com/raffles/364315","retrieved":1694506372713},{"title":"나이키 ISPA 링크 액시스 토탈 오렌지 앤 소닉 옐로우","contents":"NIKE US","link":"https://www.shoeprize.com/raffles/119888","retrieved":1694445023329},{"title":"에어 조던 4 레트로 TD 카카오 와우","contents":"DTLR","link":"https://www.shoeprize.com/raffles/364316","retrieved":1694445023308},{"title":"에어 조던 4 레트로 PS 카카오 와우","contents":"DTLR","link":"https://www.shoeprize.com/raffles/364317","retrieved":1694445023313},{"title":"에어 조던 4 GS 카카오 와우","contents":"DTLR","link":"https://www.shoeprize.com/raffles/102571","retrieved":1694445023310},{"title":"에어 조던 4 레트로 TD 카카오 와우","contents":"SHOE PALACE","link":"https://www.shoeprize.com/raffles/364316","retrieved":1694445023308},{"title":"에어 조던 4 레트로 PS 카카오 와우","contents":"SHOE PALACE","link":"https://www.shoeprize.com/raffles/364317","retrieved":1694445023313},{"title":"에어 조던 4 GS 카카오 와우","contents":"SHOE PALACE","link":"https://www.shoeprize.com/raffles/102571","retrieved":1694445023310},{"title":"에어 조던 4 GS 카카오 와우","contents":"SHOP NICEKICKS","link":"https://www.shoeprize.com/raffles/102571","retrieved":1694445023310},{"title":"원 유니버스 페스티벌 2023","contents":"인터파크 티켓","link":"https://www.shoeprize.com/raffles/123477","retrieved":1694509814698},{"title":"원 유니버스 페스티벌 2023","contents":"네이버 예약","link":"https://www.shoeprize.com/raffles/123477","retrieved":1694509814698},{"title":"원 유니버스 페스티벌 2023","contents":"야놀자","link":"https://www.shoeprize.com/raffles/123477","retrieved":1694509814698},{"title":"나이키 에어 맥스 90 올리브 브라운","contents":"FINISHLINE","link":"https://www.shoeprize.com/raffles/117956","retrieved":1694506372737},{"title":"살로몬 XT-6 고어텍스 블랙 에보니","contents":"SLAMJAM","link":"https://www.shoeprize.com/raffles/101840","retrieved":1694506372740},{"title":"살로몬 XT-6 고어텍스 카본 베링 씨 세이지","contents":"SLAMJAM","link":"https://www.shoeprize.com/raffles/365384","retrieved":1694506372742},{"title":"아식스 젤-1130 오이스터 그레이 클레이 그레이","contents":"OFFSPRING","link":"https://www.shoeprize.com/raffles/219528","retrieved":1694506372745},{"title":"아식스 젤-1130 오이스터 그레이 클레이 그레이","contents":"OFFICE","link":"https://www.shoeprize.com/raffles/219528","retrieved":1694506372745},{"title":"에리즈 x 크록스 하이커 엑스케이프 클로그 데저트 그래스","contents":"SLAMJAM","link":"https://www.shoeprize.com/raffles/364864","retrieved":1694524365703},{"title":"에리즈 x 크록스 하이커 엑스케이프 클로그 슬레이트 그레이","contents":"SLAMJAM","link":"https://www.shoeprize.com/raffles/364865","retrieved":1694524365706}]}