{"title":"슈프라이즈 ─ 국내","url":"https://www.shoeprize.com/today/?filter={%22excludeKor%22:0,%22includeKor%22:1,%22excludeEnd%22:0}","favicon":"https://static.shoeprize.com/images/icons/appIcon/touch-icon-16x16.1d3df1c84440.png","elements":[{"title":"톰 삭스 x 나이키 제너럴 퍼포스 슈 브라운","contents":"UNDEFEATED US","link":"https://www.shoeprize.com/raffles/96647","retrieved":1675772296059},{"title":"톰 삭스 x 나이키 제너럴 퍼포스 슈 브라운","contents":"CREME 321","link":"https://www.shoeprize.com/raffles/96647","retrieved":1675772296059},{"title":"뉴발란스 650R 라이트 알루미늄","contents":"NEW BALANCE US","link":"https://www.shoeprize.com/raffles/107968","retrieved":1675782726783},{"title":"나이키 덩크 로우 우먼스 발렌타인 데이","contents":"BODEGA","link":"https://www.shoeprize.com/raffles/100355","retrieved":1675739500262},{"title":"나이키 에어 트레이너 1 소프트 핑크 앤 코코넛 밀크","contents":"BODEGA","link":"https://www.shoeprize.com/raffles/101533","retrieved":1675739500260},{"title":"톰 삭스 x 나이키 제너럴 퍼포스 슈 브라운","contents":"BODEGA","link":"https://www.shoeprize.com/raffles/96647","retrieved":1675772296059},{"title":"톰 삭스 x 나이키 제너럴 퍼포스 슈 브라운","contents":"NIKE US","link":"https://www.shoeprize.com/raffles/96647","retrieved":1675772296059},{"title":"나이키 덩크 로우 우먼스 미디엄 소프트 핑크","contents":"NIKE US","link":"https://www.shoeprize.com/raffles/104482","retrieved":1675782726795},{"title":"톰 삭스 x 나이키 제너럴 퍼포스 슈 브라운","contents":"카시나","link":"https://www.shoeprize.com/raffles/96647","retrieved":1675772296059},{"title":"에어 조던 4 레트로 우먼스 오일 그린","contents":"SVD *IN APP","link":"https://www.shoeprize.com/raffles/105239","retrieved":1675782726795},{"title":"에어 조던 헥스 뮬 SP 우먼스 라이트 실버","contents":"SVD *IN APP","link":"https://www.shoeprize.com/raffles/107878","retrieved":1675782726795},{"title":"앤더슨 벨 x 아식스 젤 소노마 15-50 브라이트 로즈 에버그린","contents":"ATMOS TOKYO","link":"https://www.shoeprize.com/raffles/101363","retrieved":1675782726795},{"title":"앤더슨 벨 x 아식스 젤 소노마 15-50 올리브 오일 다크 브라운","contents":"ATMOS TOKYO","link":"https://www.shoeprize.com/raffles/101362","retrieved":1675782726798},{"title":"앤더슨 벨 x 아식스 젤 소노마 15-50 블랙 그린","contents":"ATMOS TOKYO","link":"https://www.shoeprize.com/raffles/101364","retrieved":1675782726798},{"title":"나이키 코르테즈 우먼스 화이트 앤 블랙","contents":"ATMOS TOKYO","link":"https://www.shoeprize.com/raffles/100847","retrieved":1675782726798},{"title":"나이키 코르테즈 화이트 앤 블랙","contents":"ATMOS TOKYO","link":"https://www.shoeprize.com/raffles/107357","retrieved":1675782726800},{"title":"뉴발란스 990v2 메이드 인 USA 핑크 퍼플","contents":"END","link":"https://www.shoeprize.com/raffles/105526","retrieved":1675696286822},{"title":"에어 조던 헥스 뮬 SP 우먼스 라이트 실버","contents":"FEATURE","link":"https://www.shoeprize.com/raffles/107878","retrieved":1675782726800},{"title":"나이키 에어 포스 1 '07 우먼스 블랙 앤 서밋 화이트","contents":"FEATURE","link":"https://www.shoeprize.com/raffles/102198","retrieved":1675782726803},{"title":"유니온 x 조던 스웨터 민트 (아시아)","contents":"NIKE JP","link":"https://www.shoeprize.com/raffles/107439","retrieved":1675782726804},{"title":"유니온 x 조던 트랙 팬츠 네이비 (아시아)","contents":"NIKE JP","link":"https://www.shoeprize.com/raffles/107438","retrieved":1675782726808},{"title":"유니온 x 조던 트랙 자켓 네이비 (아시아)","contents":"NIKE JP","link":"https://www.shoeprize.com/raffles/107437","retrieved":1675782726808},{"title":"유니온 x 에어 조던 1 KO 로우 화이트","contents":"NIKE JP","link":"https://www.shoeprize.com/raffles/105338","retrieved":1675782726809},{"title":"유니온 x 조던 버킷 햇 스카이 블루","contents":"NIKE JP","link":"https://www.shoeprize.com/raffles/107294","retrieved":1675782726810},{"title":"유니온 x 조던 버킷 햇 화이트","contents":"NIKE JP","link":"https://www.shoeprize.com/raffles/107293","retrieved":1675782726811},{"title":"유니온 x 조던 버킷 햇 민트","contents":"NIKE JP","link":"https://www.shoeprize.com/raffles/107292","retrieved":1675782726812},{"title":"유니온 x 조던 버킷 햇 네이비","contents":"NIKE JP","link":"https://www.shoeprize.com/raffles/107291","retrieved":1675782726812},{"title":"나이키 에어 맥스 90 LTR 펄 핑크 바로크 브라운","contents":"ATMOS TOKYO","link":"https://www.shoeprize.com/raffles/100358","retrieved":1675782726813},{"title":"에어 조던 헥스 뮬 SP 우먼스 라이트 실버","contents":"ATMOS TOKYO","link":"https://www.shoeprize.com/raffles/107878","retrieved":1675782726814},{"title":"나이키 에어 포스 1 프리미엄 우먼스 바체타 탄","contents":"ATMOS TOKYO","link":"https://www.shoeprize.com/raffles/103049","retrieved":1675782726815}]}